odoo/addons/mrp_flattened_bom_xlsx/README.rst
odoo/addons/mrp_flattened_bom_xlsx/__init__.py
odoo/addons/mrp_flattened_bom_xlsx/__manifest__.py
odoo/addons/mrp_flattened_bom_xlsx/i18n/mrp_flattened_bom_xlsx.pot
odoo/addons/mrp_flattened_bom_xlsx/models/__init__.py
odoo/addons/mrp_flattened_bom_xlsx/models/mrp_bom.py
odoo/addons/mrp_flattened_bom_xlsx/report/__init__.py
odoo/addons/mrp_flattened_bom_xlsx/report/flattened_bom_xlsx.py
odoo/addons/mrp_flattened_bom_xlsx/report/flattened_bom_xlsx.xml
odoo/addons/mrp_flattened_bom_xlsx/static/description/icon.png
odoo/addons/mrp_flattened_bom_xlsx/tests/__init__.py
odoo/addons/mrp_flattened_bom_xlsx/tests/test_flattened_bom.py
odoo11_addon_mrp_flattened_bom_xlsx-11.0.1.0.0.99.dev3.dist-info/METADATA
odoo11_addon_mrp_flattened_bom_xlsx-11.0.1.0.0.99.dev3.dist-info/RECORD
odoo11_addon_mrp_flattened_bom_xlsx-11.0.1.0.0.99.dev3.dist-info/WHEEL
odoo11_addon_mrp_flattened_bom_xlsx-11.0.1.0.0.99.dev3.dist-info/top_level.txt
